nzl/__init__.py
nzl-0.0.0.dist-info/LICENSE
nzl-0.0.0.dist-info/METADATA
nzl-0.0.0.dist-info/WHEEL
nzl-0.0.0.dist-info/top_level.txt
nzl-0.0.0.dist-info/RECORD
