Metadata-Version: 2.1
Name: nzl
Version: 0.0.0
Summary: Nabla Zero Labs Open Source Software
Author-email: Juan Arrieta <juan.arrieta@nablazerolabs.com>
Project-URL: Homepage, https://github.com/NablaZeroLabs/nzl
Project-URL: Issues, https://github.com/NablaZeroLabs/nzl/issues
Keywords: astrodynamics
Classifier: Programming Language :: Python :: 3
Classifier: License :: OSI Approved :: MIT License
Classifier: Operating System :: OS Independent
Requires-Python: >=3.9
License-File: LICENSE
